<?xml version="1.0" encoding="UTF-8"?>
<java version="17.0.4.1" class="java.beans.XMLDecoder">
 <object class="org.eclipse.epp.internal.mpc.ui.catalog.MarketplaceInfo" id="MarketplaceInfo0">
  <void property="iuToNodeKey">
   <void method="put">
    <string>org.jboss.tools.forge.m2e.feature</string>
    <object class="java.util.ArrayList">
     <void method="add">
      <string>https://marketplace.eclipse.org#1617241</string>
     </void>
    </object>
   </void>
   <void method="put">
    <string>org.wso2.developerstudio.eclipse.registry.artifact.feature</string>
    <object class="java.util.ArrayList">
     <void method="add">
      <string>https://marketplace.eclipse.org#296419</string>
     </void>
    </object>
   </void>
   <void method="put">
    <string>org.eclipse.m2e.core.ui.phasesandgoals.feature</string>
    <object class="java.util.ArrayList">
     <void method="add">
      <string>https://marketplace.eclipse.org#2394572</string>
     </void>
    </object>
   </void>
   <void method="put">
    <string>org.wso2.developerstudio.eclipse.bpel.artifact.feature</string>
    <object class="java.util.ArrayList">
     <void method="add">
      <string>https://marketplace.eclipse.org#296419</string>
     </void>
    </object>
   </void>
   <void method="put">
    <string>org.eclipse.sirius.runtime.ide.ui</string>
    <object class="java.util.ArrayList">
     <void method="add">
      <string>https://marketplace.eclipse.org#1069</string>
     </void>
    </object>
   </void>
   <void method="put">
    <string>org.brainwy.liclipsetext.feature</string>
    <object class="java.util.ArrayList">
     <void method="add">
      <string>https://marketplace.eclipse.org#2894763</string>
     </void>
    </object>
   </void>
   <void method="put">
    <string>org.eclipse.swtbot</string>
    <object class="java.util.ArrayList">
     <void method="add">
      <string>https://marketplace.eclipse.org#677</string>
     </void>
    </object>
   </void>
   <void method="put">
    <string>org.eclipse.embedcdt.codered</string>
    <object class="java.util.ArrayList">
     <void method="add">
      <string>https://marketplace.eclipse.org#2593184</string>
     </void>
    </object>
   </void>
   <void method="put">
    <string>org.eclipse.bpmn2.modeler.examples</string>
    <object class="java.util.ArrayList">
     <void method="add">
      <string>https://marketplace.eclipse.org#2799080</string>
     </void>
    </object>
   </void>
   <void method="put">
    <string>org.eclipse.egit</string>
    <object class="java.util.ArrayList">
     <void method="add">
      <string>https://marketplace.eclipse.org#2963400</string>
     </void>
     <void method="add">
      <string>https://marketplace.eclipse.org#2963451</string>
     </void>
    </object>
   </void>
   <void method="put">
    <string>org.wso2.developerstudio.eclipse.bpel.feature</string>
    <object class="java.util.ArrayList">
     <void method="add">
      <string>https://marketplace.eclipse.org#296419</string>
     </void>
    </object>
   </void>
   <void method="put">
    <string>org.eclipse.m2e.lemminx.feature</string>
    <object class="java.util.ArrayList">
     <void method="add">
      <string>https://marketplace.eclipse.org#2963451</string>
     </void>
    </object>
   </void>
   <void method="put">
    <string>org.eclipse.sirius.specifier.ide.ui</string>
    <object class="java.util.ArrayList">
     <void method="add">
      <string>https://marketplace.eclipse.org#1069</string>
     </void>
    </object>
   </void>
   <void method="put">
    <string>org.wso2.developerstudio.eclipse.carbon.uibundle.artifact.feature</string>
    <object class="java.util.ArrayList">
     <void method="add">
      <string>https://marketplace.eclipse.org#296419</string>
     </void>
    </object>
   </void>
   <void method="put">
    <string>org.eclipse.bpmn2.modeler</string>
    <object class="java.util.ArrayList">
     <void method="add">
      <string>https://marketplace.eclipse.org#2799080</string>
     </void>
    </object>
   </void>
   <void method="put">
    <string>org.jboss.tools.cdi.feature</string>
    <object class="java.util.ArrayList">
     <void method="add">
      <string>https://marketplace.eclipse.org#1617241</string>
     </void>
    </object>
   </void>
   <void method="put">
    <string>com.aspose.cells.java.maven</string>
    <object class="java.util.ArrayList">
     <void method="add">
      <string>https://marketplace.eclipse.org#5277005</string>
     </void>
    </object>
   </void>
   <void method="put">
    <string>org.jboss.tools.fuse.transformation.feature</string>
    <object class="java.util.ArrayList">
     <void method="add">
      <string>https://marketplace.eclipse.org#1617241</string>
     </void>
    </object>
   </void>
   <void method="put">
    <string>org.wso2.developerstudio.eclipse.appserver.artifact.feature</string>
    <object class="java.util.ArrayList">
     <void method="add">
      <string>https://marketplace.eclipse.org#296419</string>
     </void>
    </object>
   </void>
   <void method="put">
    <string>org.eclipse.embedcdt.templates.sifive</string>
    <object class="java.util.ArrayList">
     <void method="add">
      <string>https://marketplace.eclipse.org#2593184</string>
     </void>
    </object>
   </void>
   <void method="put">
    <string>org.jboss.tools.cdi.microprofile.feature</string>
    <object class="java.util.ArrayList">
     <void method="add">
      <string>https://marketplace.eclipse.org#1617241</string>
     </void>
    </object>
   </void>
   <void method="put">
    <string>jsonedit-feature</string>
    <object class="java.util.ArrayList">
     <void method="add">
      <string>https://marketplace.eclipse.org#945</string>
     </void>
    </object>
   </void>
   <void method="put">
    <string>org.wso2.developerstudio.eclipse.esb.graphical.editor.feature</string>
    <object class="java.util.ArrayList">
     <void method="add">
      <string>https://marketplace.eclipse.org#296419</string>
     </void>
    </object>
   </void>
   <void method="put">
    <string>org.infinitest.eclipse.feature</string>
    <object class="java.util.ArrayList">
     <void method="add">
      <string>https://marketplace.eclipse.org#1124</string>
     </void>
    </object>
   </void>
   <void method="put">
    <string>org.eclipse.emf.validation.sdk</string>
    <object class="java.util.ArrayList">
     <void method="add">
      <string>https://marketplace.eclipse.org#1069</string>
     </void>
    </object>
   </void>
   <void method="put">
    <string>org.wso2.developerstudio.eclipse.framework.core.feature</string>
    <object class="java.util.ArrayList">
     <void method="add">
      <string>https://marketplace.eclipse.org#296419</string>
     </void>
    </object>
   </void>
   <void method="put">
    <string>org.fusesource.ide.server.extensions.feature</string>
    <object class="java.util.ArrayList">
     <void method="add">
      <string>https://marketplace.eclipse.org#1617241</string>
     </void>
    </object>
   </void>
   <void method="put">
    <string>org.testng.eclipse.maven.feature</string>
    <object class="java.util.ArrayList">
     <void method="add">
      <string>https://marketplace.eclipse.org#1549</string>
     </void>
    </object>
   </void>
   <void method="put">
    <string>org.fusesource.ide.jmx.feature</string>
    <object class="java.util.ArrayList">
     <void method="add">
      <string>https://marketplace.eclipse.org#1617241</string>
     </void>
    </object>
   </void>
   <void method="put">
    <string>org.eclipse.emf.cdo.sdk</string>
    <object class="java.util.ArrayList">
     <void method="add">
      <string>https://marketplace.eclipse.org#573</string>
     </void>
    </object>
   </void>
   <void method="put">
    <string>org.jboss.tools.openshift.cdk.feature</string>
    <object class="java.util.ArrayList">
     <void method="add">
      <string>https://marketplace.eclipse.org#1617241</string>
     </void>
    </object>
   </void>
   <void method="put">
    <string>org.nodeclipse.enide.gradle.feature</string>
    <object class="java.util.ArrayList">
     <void method="add">
      <string>https://marketplace.eclipse.org#1512180</string>
     </void>
    </object>
   </void>
   <void method="put">
    <string>com.aspose.pdf.java.maven</string>
    <object class="java.util.ArrayList">
     <void method="add">
      <string>https://marketplace.eclipse.org#5277009</string>
     </void>
    </object>
   </void>
   <void method="put">
    <string>org.eclipse.embedcdt.debug.gdbjtag.pyocd</string>
    <object class="java.util.ArrayList">
     <void method="add">
      <string>https://marketplace.eclipse.org#2593184</string>
     </void>
    </object>
   </void>
   <void method="put">
    <string>org.jboss.tools.smooks.feature</string>
    <object class="java.util.ArrayList">
     <void method="add">
      <string>https://marketplace.eclipse.org#296419</string>
     </void>
    </object>
   </void>
   <void method="put">
    <string>org.jboss.tools.maven.profiles.feature</string>
    <object class="java.util.ArrayList">
     <void method="add">
      <string>https://marketplace.eclipse.org#1286316</string>
     </void>
    </object>
   </void>
   <void method="put">
    <string>org.jboss.tools.jmx.feature</string>
    <object class="java.util.ArrayList">
     <void method="add">
      <string>https://marketplace.eclipse.org#1617241</string>
     </void>
    </object>
   </void>
   <void method="put">
    <string>org.eclipse.embedcdt.packs</string>
    <object class="java.util.ArrayList">
     <void method="add">
      <string>https://marketplace.eclipse.org#2593184</string>
     </void>
    </object>
   </void>
   <void method="put">
    <string>org.freejava.javasourceattacher.feature</string>
    <object class="java.util.ArrayList">
     <void method="add">
      <string>https://marketplace.eclipse.org#84997</string>
     </void>
    </object>
   </void>
   <void method="put">
    <string>org.eclipse.m2e.wtp.jsf.feature</string>
    <object class="java.util.ArrayList">
     <void method="add">
      <string>https://marketplace.eclipse.org#2963451</string>
     </void>
    </object>
   </void>
   <void method="put">
    <string>org.eclipse.etrice.feature</string>
    <object class="java.util.ArrayList">
     <void method="add">
      <string>https://marketplace.eclipse.org#169937</string>
     </void>
    </object>
   </void>
   <void method="put">
    <string>com.gwtplugins.eclipse.suite.v3.feature</string>
    <object class="java.util.ArrayList">
     <void method="add">
      <string>https://marketplace.eclipse.org#5579576</string>
     </void>
    </object>
   </void>
   <void method="put">
    <string>org.wso2.developerstudio.eclipse.registry.feature</string>
    <object class="java.util.ArrayList">
     <void method="add">
      <string>https://marketplace.eclipse.org#296419</string>
     </void>
    </object>
   </void>
   <void method="put">
    <string>org.jboss.tools.foundation.security.linux.feature</string>
    <object class="java.util.ArrayList">
     <void method="add">
      <string>https://marketplace.eclipse.org#1617241</string>
     </void>
    </object>
   </void>
   <void method="put">
    <string>com.equo.chromium.eclipse.feature.feature.group</string>
    <object class="java.util.ArrayList">
     <void method="add">
      <string>https://marketplace.eclipse.org#5642053</string>
     </void>
    </object>
   </void>
   <void method="put">
    <string>org.jboss.tools.openshift.feature</string>
    <object class="java.util.ArrayList">
     <void method="add">
      <string>https://marketplace.eclipse.org#1617241</string>
     </void>
    </object>
   </void>
   <void method="put">
    <string>fish.payara.eclipse.tools.micro.feature</string>
    <object class="java.util.ArrayList">
     <void method="add">
      <string>https://marketplace.eclipse.org#4014208</string>
     </void>
    </object>
   </void>
   <void method="put">
    <string>org.wso2.developerstudio.eclipse.analytics.artifact.feature</string>
    <object class="java.util.ArrayList">
     <void method="add">
      <string>https://marketplace.eclipse.org#296419</string>
     </void>
    </object>
   </void>
   <void method="put">
    <string>ContextQuickie2</string>
    <object class="java.util.ArrayList">
     <void method="add">
      <string>https://marketplace.eclipse.org#5305264</string>
     </void>
    </object>
   </void>
   <void method="put">
    <string>org.eclipse.jpt.jaxb.feature</string>
    <object class="java.util.ArrayList">
     <void method="add">
      <string>https://marketplace.eclipse.org#2963451</string>
     </void>
    </object>
   </void>
   <void method="put">
    <string>org.wso2.developerstudio.eclipse.apim.feature</string>
    <object class="java.util.ArrayList">
     <void method="add">
      <string>https://marketplace.eclipse.org#296419</string>
     </void>
    </object>
   </void>
   <void method="put">
    <string>org.jboss.tools.quarkus.feature</string>
    <object class="java.util.ArrayList">
     <void method="add">
      <string>https://marketplace.eclipse.org#1617241</string>
     </void>
    </object>
   </void>
   <void method="put">
    <string>org.eclipse.jst.server_adapters.ext.feature</string>
    <object class="java.util.ArrayList">
     <void method="add">
      <string>https://marketplace.eclipse.org#2963451</string>
     </void>
    </object>
   </void>
   <void method="put">
    <string>org.jboss.tools.common.jdt.feature</string>
    <object class="java.util.ArrayList">
     <void method="add">
      <string>https://marketplace.eclipse.org#1617241</string>
     </void>
    </object>
   </void>
   <void method="put">
    <string>org.wso2.developerstudio.eclipse.carbonserver.44.feature</string>
    <object class="java.util.ArrayList">
     <void method="add">
      <string>https://marketplace.eclipse.org#296419</string>
     </void>
    </object>
   </void>
   <void method="put">
    <string>de.bastiankrol.startexplorer.feature</string>
    <object class="java.util.ArrayList">
     <void method="add">
      <string>https://marketplace.eclipse.org#1451713</string>
     </void>
     <void method="add">
      <string>https://marketplace.eclipse.org#1512180</string>
     </void>
    </object>
   </void>
   <void method="put">
    <string>org.eclipse.egit.gitflow.feature</string>
    <object class="java.util.ArrayList">
     <void method="add">
      <string>https://marketplace.eclipse.org#2963400</string>
     </void>
     <void method="add">
      <string>https://marketplace.eclipse.org#2963451</string>
     </void>
    </object>
   </void>
   <void method="put">
    <string>org.jboss.tools.vpe.feature</string>
    <object class="java.util.ArrayList">
     <void method="add">
      <string>https://marketplace.eclipse.org#1617241</string>
     </void>
    </object>
   </void>
   <void method="put">
    <string>org.eclipse.wst.jsdt.chromium.debug.feature</string>
    <object class="java.util.ArrayList">
     <void method="add">
      <string>https://marketplace.eclipse.org#1617241</string>
     </void>
    </object>
   </void>
   <void method="put">
    <string>org.wso2.developerstudio.eclipse.appfactory.feature</string>
    <object class="java.util.ArrayList">
     <void method="add">
      <string>https://marketplace.eclipse.org#296419</string>
     </void>
    </object>
   </void>
   <void method="put">
    <string>org.eclipse.m2e.wtp.jpa.feature</string>
    <object class="java.util.ArrayList">
     <void method="add">
      <string>https://marketplace.eclipse.org#2963451</string>
     </void>
    </object>
   </void>
   <void method="put">
    <string>org.wso2.developerstudio.eclipse.brs.artifact.feature</string>
    <object class="java.util.ArrayList">
     <void method="add">
      <string>https://marketplace.eclipse.org#296419</string>
     </void>
    </object>
   </void>
   <void method="put">
    <string>org.wso2.developerstudio.eclipse.carbonserver.32.feature</string>
    <object class="java.util.ArrayList">
     <void method="add">
      <string>https://marketplace.eclipse.org#296419</string>
     </void>
    </object>
   </void>
   <void method="put">
    <string>org.wso2.developerstudio.eclipse.carbonserver.remote.feature</string>
    <object class="java.util.ArrayList">
     <void method="add">
      <string>https://marketplace.eclipse.org#296419</string>
     </void>
    </object>
   </void>
   <void method="put">
    <string>org.jboss.tools.maven.springboot.feature</string>
    <object class="java.util.ArrayList">
     <void method="add">
      <string>https://marketplace.eclipse.org#1617241</string>
     </void>
    </object>
   </void>
   <void method="put">
    <string>com.gwtplugins.eclipse.sdkbundle.gwt28.feature</string>
    <object class="java.util.ArrayList">
     <void method="add">
      <string>https://marketplace.eclipse.org#5579576</string>
     </void>
    </object>
   </void>
   <void method="put">
    <string>org.eclipse.embedcdt.debug.gdbjtag.jlink</string>
    <object class="java.util.ArrayList">
     <void method="add">
      <string>https://marketplace.eclipse.org#2593184</string>
     </void>
    </object>
   </void>
   <void method="put">
    <string>com.jboss.devstudio.fuse.feature</string>
    <object class="java.util.ArrayList">
     <void method="add">
      <string>https://marketplace.eclipse.org#1616973</string>
     </void>
    </object>
   </void>
   <void method="put">
    <string>org.wso2.developerstudio.eclipse.ds.feature</string>
    <object class="java.util.ArrayList">
     <void method="add">
      <string>https://marketplace.eclipse.org#296419</string>
     </void>
    </object>
   </void>
   <void method="put">
    <string>org.eclipse.jst.ws.jaxws.feature</string>
    <object class="java.util.ArrayList">
     <void method="add">
      <string>https://marketplace.eclipse.org#2963451</string>
     </void>
    </object>
   </void>
   <void method="put">
    <string>org.fusesource.ide.camel.editor.feature</string>
    <object class="java.util.ArrayList">
     <void method="add">
      <string>https://marketplace.eclipse.org#1617241</string>
     </void>
    </object>
   </void>
   <void method="put">
    <string>org.moreunit</string>
    <object class="java.util.ArrayList">
     <void method="add">
      <string>https://marketplace.eclipse.org#194</string>
     </void>
    </object>
   </void>
   <void method="put">
    <string>pm.eclipse.editbox.feature</string>
    <object class="java.util.ArrayList">
     <void method="add">
      <string>https://marketplace.eclipse.org#1451713</string>
     </void>
     <void method="add">
      <string>https://marketplace.eclipse.org#1512180</string>
     </void>
    </object>
   </void>
   <void method="put">
    <string>org.jboss.tools.cdi.deltaspike.feature</string>
    <object class="java.util.ArrayList">
     <void method="add">
      <string>https://marketplace.eclipse.org#1617241</string>
     </void>
    </object>
   </void>
   <void method="put">
    <string>org.wso2.developerstudio.eclipse.gadget.artifact.feature</string>
    <object class="java.util.ArrayList">
     <void method="add">
      <string>https://marketplace.eclipse.org#296419</string>
     </void>
    </object>
   </void>
   <void method="put">
    <string>org.eclipse.wst.json_ui.feature</string>
    <object class="java.util.ArrayList">
     <void method="add">
      <string>https://marketplace.eclipse.org#2963400</string>
     </void>
     <void method="add">
      <string>https://marketplace.eclipse.org#2963451</string>
     </void>
     <void method="add">
      <string>https://marketplace.eclipse.org#1617241</string>
     </void>
    </object>
   </void>
   <void method="put">
    <string>fr.obeo.dsl.designer.ce.feature</string>
    <object class="java.util.ArrayList">
     <void method="add">
      <string>https://marketplace.eclipse.org#1069</string>
     </void>
    </object>
   </void>
   <void method="put">
    <string>org.eclipse.m2e.feature</string>
    <object class="java.util.ArrayList">
     <void method="add">
      <string>https://marketplace.eclipse.org#5321178</string>
     </void>
    </object>
   </void>
   <void method="put">
    <string>org.jboss.tools.maven.jbosspackaging.feature</string>
    <object class="java.util.ArrayList">
     <void method="add">
      <string>https://marketplace.eclipse.org#1617241</string>
     </void>
    </object>
   </void>
   <void method="put">
    <string>com.eco.bio7.ijmacroedit.feature</string>
    <object class="java.util.ArrayList">
     <void method="add">
      <string>https://marketplace.eclipse.org#3103502</string>
     </void>
    </object>
   </void>
   <void method="put">
    <string> org.eclipse.m2e.pde.feature</string>
    <object class="java.util.ArrayList">
     <void method="add">
      <string>https://marketplace.eclipse.org#5321178</string>
     </void>
    </object>
   </void>
   <void method="put">
    <string>org.apache.directory.studio.ldapbrowser.feature</string>
    <object class="java.util.ArrayList">
     <void method="add">
      <string>https://marketplace.eclipse.org#319</string>
     </void>
    </object>
   </void>
   <void method="put">
    <string>org.eclipse.embedcdt.templates.xpack</string>
    <object class="java.util.ArrayList">
     <void method="add">
      <string>https://marketplace.eclipse.org#2593184</string>
     </void>
    </object>
   </void>
   <void method="put">
    <string>org.jboss.tools.jsf.feature</string>
    <object class="java.util.ArrayList">
     <void method="add">
      <string>https://marketplace.eclipse.org#1617241</string>
     </void>
    </object>
   </void>
   <void method="put">
    <string>org.jboss.tools.openshift.js.feature</string>
    <object class="java.util.ArrayList">
     <void method="add">
      <string>https://marketplace.eclipse.org#1617241</string>
     </void>
    </object>
   </void>
   <void method="put">
    <string>org.nodeclipse.enide.editors.gradle.feature</string>
    <object class="java.util.ArrayList">
     <void method="add">
      <string>https://marketplace.eclipse.org#1512180</string>
     </void>
    </object>
   </void>
   <void method="put">
    <string>org.fusesource.ide.core.feature</string>
    <object class="java.util.ArrayList">
     <void method="add">
      <string>https://marketplace.eclipse.org#1617241</string>
     </void>
    </object>
   </void>
   <void method="put">
    <string>org.eclipse.wst.server_adapters.feature</string>
    <object class="java.util.ArrayList">
     <void method="add">
      <string>https://marketplace.eclipse.org#2963400</string>
     </void>
     <void method="add">
      <string>https://marketplace.eclipse.org#2963451</string>
     </void>
    </object>
   </void>
   <void method="put">
    <string>org.smooks.edi.editor-feature</string>
    <object class="java.util.ArrayList">
     <void method="add">
      <string>https://marketplace.eclipse.org#296419</string>
     </void>
    </object>
   </void>
   <void method="put">
    <string>bndtools.main.feature</string>
    <object class="java.util.ArrayList">
     <void method="add">
      <string>https://marketplace.eclipse.org#1220</string>
     </void>
    </object>
   </void>
   <void method="put">
    <string>org.eclipse.sirius.runtime.acceleo</string>
    <object class="java.util.ArrayList">
     <void method="add">
      <string>https://marketplace.eclipse.org#1069</string>
     </void>
    </object>
   </void>
   <void method="put">
    <string>org.jboss.tools.m2e.wro4j.feature</string>
    <object class="java.util.ArrayList">
     <void method="add">
      <string>https://marketplace.eclipse.org#807489</string>
     </void>
    </object>
   </void>
   <void method="put">
    <string>org.jboss.tools.maven.hibernate.feature</string>
    <object class="java.util.ArrayList">
     <void method="add">
      <string>https://marketplace.eclipse.org#1617241</string>
     </void>
    </object>
   </void>
   <void method="put">
    <string>org.eclipse.etrice.cdt_integration.feature</string>
    <object class="java.util.ArrayList">
     <void method="add">
      <string>https://marketplace.eclipse.org#169937</string>
     </void>
    </object>
   </void>
   <void method="put">
    <string>org.wso2.developerstudio.eclipse.ds.artifact.feature</string>
    <object class="java.util.ArrayList">
     <void method="add">
      <string>https://marketplace.eclipse.org#296419</string>
     </void>
    </object>
   </void>
   <void method="put">
    <string>bndtools.m2e.feature</string>
    <object class="java.util.ArrayList">
     <void method="add">
      <string>https://marketplace.eclipse.org#1220</string>
     </void>
    </object>
   </void>
   <void method="put">
    <string>org.jboss.ide.eclipse.archives.feature</string>
    <object class="java.util.ArrayList">
     <void method="add">
      <string>https://marketplace.eclipse.org#1617241</string>
     </void>
    </object>
   </void>
   <void method="put">
    <string>com.eco.bio7.image.feature</string>
    <object class="java.util.ArrayList">
     <void method="add">
      <string>https://marketplace.eclipse.org#3103502</string>
     </void>
    </object>
   </void>
   <void method="put">
    <string>org.jboss.tools.usage.feature</string>
    <object class="java.util.ArrayList">
     <void method="add">
      <string>https://marketplace.eclipse.org#1617241</string>
     </void>
    </object>
   </void>
   <void method="put">
    <string>org.eclipse.tips.feature</string>
    <object class="java.util.ArrayList">
     <void method="add">
      <string>https://marketplace.eclipse.org#2963400</string>
     </void>
     <void method="add">
      <string>https://marketplace.eclipse.org#2963451</string>
     </void>
    </object>
   </void>
   <void method="put">
    <string>org.jboss.tools.community.project.examples.feature</string>
    <object class="java.util.ArrayList">
     <void method="add">
      <string>https://marketplace.eclipse.org#1617241</string>
     </void>
    </object>
   </void>
   <void method="put">
    <string>de.jcup.hijson</string>
    <object class="java.util.ArrayList">
     <void method="add">
      <string>https://marketplace.eclipse.org#5223289</string>
     </void>
    </object>
   </void>
   <void method="put">
    <string>com.aspose.tasks.java.maven</string>
    <object class="java.util.ArrayList">
     <void method="add">
      <string>https://marketplace.eclipse.org#5277026</string>
     </void>
    </object>
   </void>
   <void method="put">
    <string>org.eclipse.wst.server_ui.feature</string>
    <object class="java.util.ArrayList">
     <void method="add">
      <string>https://marketplace.eclipse.org#2963400</string>
     </void>
     <void method="add">
      <string>https://marketplace.eclipse.org#2963451</string>
     </void>
    </object>
   </void>
   <void method="put">
    <string>org.eclipse.jpt.common.eclipselink.feature</string>
    <object class="java.util.ArrayList">
     <void method="add">
      <string>https://marketplace.eclipse.org#2963451</string>
     </void>
    </object>
   </void>
   <void method="put">
    <string>com.equo.chromium.feature.feature.group</string>
    <object class="java.util.ArrayList">
     <void method="add">
      <string>https://marketplace.eclipse.org#5642053</string>
     </void>
    </object>
   </void>
   <void method="put">
    <string>org.jboss.tools.maven.feature</string>
    <object class="java.util.ArrayList">
     <void method="add">
      <string>https://marketplace.eclipse.org#1617241</string>
     </void>
    </object>
   </void>
   <void method="put">
    <string>org.eclipse.embedcdt.debug.gdbjtag.openocd</string>
    <object class="java.util.ArrayList">
     <void method="add">
      <string>https://marketplace.eclipse.org#2593184</string>
     </void>
    </object>
   </void>
   <void method="put">
    <string>org.jboss.tools.openshift.egit.integration.feature</string>
    <object class="java.util.ArrayList">
     <void method="add">
      <string>https://marketplace.eclipse.org#1617241</string>
     </void>
    </object>
   </void>
   <void method="put">
    <string>org.eclipse.jst.web_js_support.feature</string>
    <object class="java.util.ArrayList">
     <void method="add">
      <string>https://marketplace.eclipse.org#2963451</string>
     </void>
    </object>
   </void>
   <void method="put">
    <string>org.jboss.tools.maven.jdt.feature</string>
    <object class="java.util.ArrayList">
     <void method="add">
      <string>https://marketplace.eclipse.org#1617241</string>
     </void>
    </object>
   </void>
   <void method="put">
    <string>org.jboss.tools.jst.feature</string>
    <object class="java.util.ArrayList">
     <void method="add">
      <string>https://marketplace.eclipse.org#1617241</string>
     </void>
    </object>
   </void>
   <void method="put">
    <string>com.wamas.ide.launching.feature</string>
    <object class="java.util.ArrayList">
     <void method="add">
      <string>https://marketplace.eclipse.org#3348921</string>
     </void>
    </object>
   </void>
   <void method="put">
    <string>org.eclipse.embedcdt.managedbuild.cross.arm</string>
    <object class="java.util.ArrayList">
     <void method="add">
      <string>https://marketplace.eclipse.org#2593184</string>
     </void>
    </object>
   </void>
   <void method="put">
    <string>org.eclipse.wst.jsdt.feature</string>
    <object class="java.util.ArrayList">
     <void method="add">
      <string>https://marketplace.eclipse.org#1617241</string>
     </void>
    </object>
   </void>
   <void method="put">
    <string>org.jboss.tools.richfaces.feature</string>
    <object class="java.util.ArrayList">
     <void method="add">
      <string>https://marketplace.eclipse.org#1617241</string>
     </void>
    </object>
   </void>
   <void method="put">
    <string>org.eclipse.sirius.samples</string>
    <object class="java.util.ArrayList">
     <void method="add">
      <string>https://marketplace.eclipse.org#1069</string>
     </void>
    </object>
   </void>
   <void method="put">
    <string>cn.ieclipse.adt.ext.feature</string>
    <object class="java.util.ArrayList">
     <void method="add">
      <string>https://marketplace.eclipse.org#393519</string>
     </void>
    </object>
   </void>
   <void method="put">
    <string>org.jboss.tools.maven.project.examples.feature</string>
    <object class="java.util.ArrayList">
     <void method="add">
      <string>https://marketplace.eclipse.org#1617241</string>
     </void>
    </object>
   </void>
   <void method="put">
    <string>com.github.sdbg.feature</string>
    <object class="java.util.ArrayList">
     <void method="add">
      <string>https://marketplace.eclipse.org#5579576</string>
     </void>
    </object>
   </void>
   <void method="put">
    <string>com.devepos.adt.codesearch</string>
    <object class="java.util.ArrayList">
     <void method="add">
      <string>https://marketplace.eclipse.org#5507008</string>
     </void>
    </object>
   </void>
   <void method="put">
    <string>org.eclipse.jsf.feature</string>
    <object class="java.util.ArrayList">
     <void method="add">
      <string>https://marketplace.eclipse.org#2963451</string>
     </void>
    </object>
   </void>
   <void method="put">
    <string>org.eclipse.buildship</string>
    <object class="java.util.ArrayList">
     <void method="add">
      <string>https://marketplace.eclipse.org#2963451</string>
     </void>
     <void method="add">
      <string>https://marketplace.eclipse.org#1617241</string>
     </void>
    </object>
   </void>
   <void method="put">
    <string>org.eclipse.wst.web_ui.feature</string>
    <object class="java.util.ArrayList">
     <void method="add">
      <string>https://marketplace.eclipse.org#2963400</string>
     </void>
     <void method="add">
      <string>https://marketplace.eclipse.org#2963451</string>
     </void>
    </object>
   </void>
   <void method="put">
    <string>org.eclipse.objectteams.otequinox.feature.group</string>
    <object class="java.util.ArrayList">
     <void method="add">
      <string>https://marketplace.eclipse.org#279</string>
     </void>
    </object>
   </void>
   <void method="put">
    <string>org.eclipse.embedcdt.templates.cortexm</string>
    <object class="java.util.ArrayList">
     <void method="add">
      <string>https://marketplace.eclipse.org#2593184</string>
     </void>
    </object>
   </void>
   <void method="put">
    <string>org.eclipse.linuxtools.docker.feature</string>
    <object class="java.util.ArrayList">
     <void method="add">
      <string>https://marketplace.eclipse.org#2963451</string>
     </void>
     <void method="add">
      <string>https://marketplace.eclipse.org#1617241</string>
     </void>
    </object>
   </void>
   <void method="put">
    <string>org.jboss.tools.foundation.feature</string>
    <object class="java.util.ArrayList">
     <void method="add">
      <string>https://marketplace.eclipse.org#1617241</string>
     </void>
    </object>
   </void>
   <void method="put">
    <string>org.jboss.tools.ws.jaxrs.feature</string>
    <object class="java.util.ArrayList">
     <void method="add">
      <string>https://marketplace.eclipse.org#1617241</string>
     </void>
    </object>
   </void>
   <void method="put">
    <string>org.eclipse.embedcdt.managedbuild.cross.riscv</string>
    <object class="java.util.ArrayList">
     <void method="add">
      <string>https://marketplace.eclipse.org#2593184</string>
     </void>
    </object>
   </void>
   <void method="put">
    <string>org.eclipse.m2e.wtp.feature</string>
    <object class="java.util.ArrayList">
     <void method="add">
      <string>https://marketplace.eclipse.org#2963451</string>
     </void>
     <void method="add">
      <string>https://marketplace.eclipse.org#1789419</string>
     </void>
    </object>
   </void>
   <void method="put">
    <string>org.jboss.tools.ws.jaxws.feature</string>
    <object class="java.util.ArrayList">
     <void method="add">
      <string>https://marketplace.eclipse.org#1617241</string>
     </void>
    </object>
   </void>
   <void method="put">
    <string>org.eclipse.jpt.common.feature</string>
    <object class="java.util.ArrayList">
     <void method="add">
      <string>https://marketplace.eclipse.org#2963451</string>
     </void>
    </object>
   </void>
   <void method="put">
    <string>org.eclipse.swtbot.eclipse</string>
    <object class="java.util.ArrayList">
     <void method="add">
      <string>https://marketplace.eclipse.org#677</string>
     </void>
    </object>
   </void>
   <void method="put">
    <string>org.eclipse.gmf.runtime.sdk</string>
    <object class="java.util.ArrayList">
     <void method="add">
      <string>https://marketplace.eclipse.org#1069</string>
     </void>
    </object>
   </void>
   <void method="put">
    <string>org.jboss.tools.project.examples.feature</string>
    <object class="java.util.ArrayList">
     <void method="add">
      <string>https://marketplace.eclipse.org#1617241</string>
     </void>
    </object>
   </void>
   <void method="put">
    <string>org.antlr.v4</string>
    <object class="java.util.ArrayList">
     <void method="add">
      <string>https://marketplace.eclipse.org#945</string>
     </void>
    </object>
   </void>
   <void method="put">
    <string>org.projectusus.autotestsuite</string>
    <object class="java.util.ArrayList">
     <void method="add">
      <string>https://marketplace.eclipse.org#1089</string>
     </void>
    </object>
   </void>
   <void method="put">
    <string>org.wso2.soapui.feature</string>
    <object class="java.util.ArrayList">
     <void method="add">
      <string>https://marketplace.eclipse.org#296419</string>
     </void>
    </object>
   </void>
   <void method="put">
    <string>org.eclipse.wildwebdeveloper.feature</string>
    <object class="java.util.ArrayList">
     <void method="add">
      <string>https://marketplace.eclipse.org#2963400</string>
     </void>
     <void method="add">
      <string>https://marketplace.eclipse.org#2963451</string>
     </void>
     <void method="add">
      <string>https://marketplace.eclipse.org#1617241</string>
     </void>
     <void method="add">
      <string>https://marketplace.eclipse.org#5578890</string>
     </void>
    </object>
   </void>
   <void method="put">
    <string>org.wso2.developerstudio.eclipse.server.framework.feature</string>
    <object class="java.util.ArrayList">
     <void method="add">
      <string>https://marketplace.eclipse.org#296419</string>
     </void>
    </object>
   </void>
   <void method="put">
    <string>org.jboss.tools.websockets.feature</string>
    <object class="java.util.ArrayList">
     <void method="add">
      <string>https://marketplace.eclipse.org#1617241</string>
     </void>
    </object>
   </void>
   <void method="put">
    <string>org.eclipse.jpt.jaxb.eclipselink.feature</string>
    <object class="java.util.ArrayList">
     <void method="add">
      <string>https://marketplace.eclipse.org#2963451</string>
     </void>
    </object>
   </void>
   <void method="put">
    <string>org.apache.directory.studio.apacheds.feature</string>
    <object class="java.util.ArrayList">
     <void method="add">
      <string>https://marketplace.eclipse.org#319</string>
     </void>
    </object>
   </void>
   <void method="put">
    <string>org.eclipse.embedcdt.debug.gdbjtag.qemu</string>
    <object class="java.util.ArrayList">
     <void method="add">
      <string>https://marketplace.eclipse.org#2593184</string>
     </void>
    </object>
   </void>
   <void method="put">
    <string>org.wso2.developerstudio.eclipse.carbonserver.31.feature</string>
    <object class="java.util.ArrayList">
     <void method="add">
      <string>https://marketplace.eclipse.org#296419</string>
     </void>
    </object>
   </void>
   <void method="put">
    <string>org.wso2.developerstudio.eclipse.artifact.library.feature</string>
    <object class="java.util.ArrayList">
     <void method="add">
      <string>https://marketplace.eclipse.org#296419</string>
     </void>
    </object>
   </void>
   <void method="put">
    <string>de.jcup.yamleditor</string>
    <object class="java.util.ArrayList">
     <void method="add">
      <string>https://marketplace.eclipse.org#4101183</string>
     </void>
    </object>
   </void>
   <void method="put">
    <string>org.eclipse.objectteams.otdt.feature.group</string>
    <object class="java.util.ArrayList">
     <void method="add">
      <string>https://marketplace.eclipse.org#279</string>
     </void>
    </object>
   </void>
   <void method="put">
    <string>org.eclipse.jst.server_ui.feature</string>
    <object class="java.util.ArrayList">
     <void method="add">
      <string>https://marketplace.eclipse.org#2963451</string>
     </void>
    </object>
   </void>
   <void method="put">
    <string>org.eclipse.wildwebdeveloper.embedder.node.feature</string>
    <object class="java.util.ArrayList">
     <void method="add">
      <string>https://marketplace.eclipse.org#2963400</string>
     </void>
     <void method="add">
      <string>https://marketplace.eclipse.org#2963451</string>
     </void>
     <void method="add">
      <string>https://marketplace.eclipse.org#5578890</string>
     </void>
    </object>
   </void>
   <void method="put">
    <string>org.jboss.tools.maven.cdi.feature</string>
    <object class="java.util.ArrayList">
     <void method="add">
      <string>https://marketplace.eclipse.org#1617241</string>
     </void>
    </object>
   </void>
   <void method="put">
    <string>com.gwtplugins.eclipse.sdkbundle.gwt27.feature</string>
    <object class="java.util.ArrayList">
     <void method="add">
      <string>https://marketplace.eclipse.org#5579576</string>
     </void>
    </object>
   </void>
   <void method="put">
    <string>org.eclipse.emf.cdo.lm</string>
    <object class="java.util.ArrayList">
     <void method="add">
      <string>https://marketplace.eclipse.org#573</string>
     </void>
    </object>
   </void>
   <void method="put">
    <string>com.aspose.barcode.java.maven</string>
    <object class="java.util.ArrayList">
     <void method="add">
      <string>https://marketplace.eclipse.org#5277018</string>
     </void>
    </object>
   </void>
   <void method="put">
    <string>org.eclipse.emf.compare.ide.ui</string>
    <object class="java.util.ArrayList">
     <void method="add">
      <string>https://marketplace.eclipse.org#1069</string>
     </void>
    </object>
   </void>
   <void method="put">
    <string>org.eclipse.swtbot.ide</string>
    <object class="java.util.ArrayList">
     <void method="add">
      <string>https://marketplace.eclipse.org#677</string>
     </void>
    </object>
   </void>
   <void method="put">
    <string>org.wso2.tcpmon.feature</string>
    <object class="java.util.ArrayList">
     <void method="add">
      <string>https://marketplace.eclipse.org#296419</string>
     </void>
    </object>
   </void>
   <void method="put">
    <string>org.eclipse.sirius.runtime.ide.eef</string>
    <object class="java.util.ArrayList">
     <void method="add">
      <string>https://marketplace.eclipse.org#1069</string>
     </void>
    </object>
   </void>
   <void method="put">
    <string>com.eco.bio7.jfxswt.feature</string>
    <object class="java.util.ArrayList">
     <void method="add">
      <string>https://marketplace.eclipse.org#3103502</string>
     </void>
    </object>
   </void>
   <void method="put">
    <string>org.eclipse.jst.ws.cxf.feature</string>
    <object class="java.util.ArrayList">
     <void method="add">
      <string>https://marketplace.eclipse.org#2963451</string>
     </void>
    </object>
   </void>
   <void method="put">
    <string>org.wso2.developerstudio.eclipse.jaggery.artifact.feature</string>
    <object class="java.util.ArrayList">
     <void method="add">
      <string>https://marketplace.eclipse.org#296419</string>
     </void>
    </object>
   </void>
   <void method="put">
    <string>org.eclipse.wst.web_ui.feature.feature.group</string>
    <object class="java.util.ArrayList">
     <void method="add">
      <string>https://marketplace.eclipse.org#1166</string>
     </void>
    </object>
   </void>
   <void method="put">
    <string>org.jboss.tools.maven.sourcelookup.feature</string>
    <object class="java.util.ArrayList">
     <void method="add">
      <string>https://marketplace.eclipse.org#1617241</string>
     </void>
    </object>
   </void>
   <void method="put">
    <string>org.jboss.tools.forge.feature</string>
    <object class="java.util.ArrayList">
     <void method="add">
      <string>https://marketplace.eclipse.org#1617241</string>
     </void>
    </object>
   </void>
   <void method="put">
    <string>org.eclipse.bpmn2.modeler.runtime.jboss</string>
    <object class="java.util.ArrayList">
     <void method="add">
      <string>https://marketplace.eclipse.org#2799080</string>
     </void>
    </object>
   </void>
   <void method="put">
    <string>org.eclipse.jst.web_ui.feature</string>
    <object class="java.util.ArrayList">
     <void method="add">
      <string>https://marketplace.eclipse.org#2963451</string>
     </void>
    </object>
   </void>
   <void method="put">
    <string>org.eclipse.wst.xsl.feature</string>
    <object class="java.util.ArrayList">
     <void method="add">
      <string>https://marketplace.eclipse.org#2963400</string>
     </void>
     <void method="add">
      <string>https://marketplace.eclipse.org#2963451</string>
     </void>
    </object>
   </void>
   <void method="put">
    <string>org.wso2.developerstudio.eclipse.security.artifact.feature</string>
    <object class="java.util.ArrayList">
     <void method="add">
      <string>https://marketplace.eclipse.org#296419</string>
     </void>
    </object>
   </void>
   <void method="put">
    <string>org.wso2.developerstudio.eclipse.carbonserver.40.feature</string>
    <object class="java.util.ArrayList">
     <void method="add">
      <string>https://marketplace.eclipse.org#296419</string>
     </void>
    </object>
   </void>
   <void method="put">
    <string>org.moreunit.light</string>
    <object class="java.util.ArrayList">
     <void method="add">
      <string>https://marketplace.eclipse.org#194</string>
     </void>
    </object>
   </void>
   <void method="put">
    <string>org.eclipse.jst.enterprise_ui.feature</string>
    <object class="java.util.ArrayList">
     <void method="add">
      <string>https://marketplace.eclipse.org#2963451</string>
     </void>
    </object>
   </void>
   <void method="put">
    <string>org.jboss.tools.common.launcher.feature</string>
    <object class="java.util.ArrayList">
     <void method="add">
      <string>https://marketplace.eclipse.org#1617241</string>
     </void>
    </object>
   </void>
   <void method="put">
    <string>org.wso2.developerstudio.eclipse.distribution.project.feature</string>
    <object class="java.util.ArrayList">
     <void method="add">
      <string>https://marketplace.eclipse.org#296419</string>
     </void>
    </object>
   </void>
   <void method="put">
    <string>org.eclipse.jst.ws.jaxws.dom.feature</string>
    <object class="java.util.ArrayList">
     <void method="add">
      <string>https://marketplace.eclipse.org#2963451</string>
     </void>
    </object>
   </void>
   <void method="put">
    <string>org.eclipse.jst.ws.axis2tools.feature</string>
    <object class="java.util.ArrayList">
     <void method="add">
      <string>https://marketplace.eclipse.org#2963451</string>
     </void>
    </object>
   </void>
   <void method="put">
    <string>fish.payara.eclipse.tools.server.feature</string>
    <object class="java.util.ArrayList">
     <void method="add">
      <string>https://marketplace.eclipse.org#4014208</string>
     </void>
    </object>
   </void>
   <void method="put">
    <string>org.testng.eclipse</string>
    <object class="java.util.ArrayList">
     <void method="add">
      <string>https://marketplace.eclipse.org#1549</string>
     </void>
    </object>
   </void>
   <void method="put">
    <string>org.fusesource.ide.syndesis.extension.feature</string>
    <object class="java.util.ArrayList">
     <void method="add">
      <string>https://marketplace.eclipse.org#1617241</string>
     </void>
    </object>
   </void>
   <void method="put">
    <string>org.wso2.developerstudio.eclipse.registry.connector.feature</string>
    <object class="java.util.ArrayList">
     <void method="add">
      <string>https://marketplace.eclipse.org#296419</string>
     </void>
    </object>
   </void>
   <void method="put">
    <string>com.aspose.email.java.maven</string>
    <object class="java.util.ArrayList">
     <void method="add">
      <string>https://marketplace.eclipse.org#5277020</string>
     </void>
    </object>
   </void>
   <void method="put">
    <string>org.eclipse.viatra.query.sdk.feature.source.feature.group</string>
    <object class="java.util.ArrayList">
     <void method="add">
      <string>https://marketplace.eclipse.org#2292729</string>
     </void>
    </object>
   </void>
   <void method="put">
    <string>org.jboss.tools.jst.jsdt.feature</string>
    <object class="java.util.ArrayList">
     <void method="add">
      <string>https://marketplace.eclipse.org#1617241</string>
     </void>
    </object>
   </void>
   <void method="put">
    <string>bndtools.pde.feature</string>
    <object class="java.util.ArrayList">
     <void method="add">
      <string>https://marketplace.eclipse.org#1220</string>
     </void>
    </object>
   </void>
   <void method="put">
    <string>org.eclipse.embedcdt.templates.stm</string>
    <object class="java.util.ArrayList">
     <void method="add">
      <string>https://marketplace.eclipse.org#2593184</string>
     </void>
    </object>
   </void>
   <void method="put">
    <string>org.eclipse.swtbot.eclipse.gef</string>
    <object class="java.util.ArrayList">
     <void method="add">
      <string>https://marketplace.eclipse.org#677</string>
     </void>
    </object>
   </void>
   <void method="put">
    <string>org.eclipse.jpt.jpa.eclipselink.feature</string>
    <object class="java.util.ArrayList">
     <void method="add">
      <string>https://marketplace.eclipse.org#2963451</string>
     </void>
    </object>
   </void>
   <void method="put">
    <string>org.nodeclipse.enide.maven.feature</string>
    <object class="java.util.ArrayList">
     <void method="add">
      <string>https://marketplace.eclipse.org#1451713</string>
     </void>
    </object>
   </void>
   <void method="put">
    <string>org.jboss.tools.stacks.core.feature</string>
    <object class="java.util.ArrayList">
     <void method="add">
      <string>https://marketplace.eclipse.org#1617241</string>
     </void>
    </object>
   </void>
   <void method="put">
    <string>org.apache.directory.studio.ldifeditor.feature</string>
    <object class="java.util.ArrayList">
     <void method="add">
      <string>https://marketplace.eclipse.org#319</string>
     </void>
    </object>
   </void>
   <void method="put">
    <string>org.eclipse.mylyn.wikitext.editors_feature</string>
    <object class="java.util.ArrayList">
     <void method="add">
      <string>https://marketplace.eclipse.org#2963451</string>
     </void>
    </object>
   </void>
   <void method="put">
    <string>org.eclipse.viatra.query.sdk.extensions.feature</string>
    <object class="java.util.ArrayList">
     <void method="add">
      <string>https://marketplace.eclipse.org#2292729</string>
     </void>
    </object>
   </void>
   <void method="put">
    <string>net.holmconsulting.ftp.server.feature</string>
    <object class="java.util.ArrayList">
     <void method="add">
      <string>https://marketplace.eclipse.org#304652</string>
     </void>
    </object>
   </void>
   <void method="put">
    <string>org.eclipse.net4j.sdk</string>
    <object class="java.util.ArrayList">
     <void method="add">
      <string>https://marketplace.eclipse.org#573</string>
     </void>
     <void method="add">
      <string>https://marketplace.eclipse.org#4002</string>
     </void>
    </object>
   </void>
   <void method="put">
    <string>eu.jsparrow.202106.feature</string>
    <object class="java.util.ArrayList">
     <void method="add">
      <string>https://marketplace.eclipse.org#3503691</string>
     </void>
    </object>
   </void>
   <void method="put">
    <string>org.eclipse.m2e.logback.feature</string>
    <object class="java.util.ArrayList">
     <void method="add">
      <string>https://marketplace.eclipse.org#2963451</string>
     </void>
    </object>
   </void>
   <void method="put">
    <string>org.eclipse.wst.xml_ui.feature</string>
    <object class="java.util.ArrayList">
     <void method="add">
      <string>https://marketplace.eclipse.org#2963400</string>
     </void>
     <void method="add">
      <string>https://marketplace.eclipse.org#2963451</string>
     </void>
    </object>
   </void>
   <void method="put">
    <string>com.aspose.slides.java.maven</string>
    <object class="java.util.ArrayList">
     <void method="add">
      <string>https://marketplace.eclipse.org#5277033</string>
     </void>
    </object>
   </void>
   <void method="put">
    <string>org.wso2.developerstudio.eclipse.framework.samples.feature</string>
    <object class="java.util.ArrayList">
     <void method="add">
      <string>https://marketplace.eclipse.org#296419</string>
     </void>
    </object>
   </void>
   <void method="put">
    <string>org.eclipse.wst.web_js_support.feature</string>
    <object class="java.util.ArrayList">
     <void method="add">
      <string>https://marketplace.eclipse.org#2963400</string>
     </void>
     <void method="add">
      <string>https://marketplace.eclipse.org#2963451</string>
     </void>
    </object>
   </void>
   <void method="put">
    <string>org.jboss.tools.jst.angularjs.feature</string>
    <object class="java.util.ArrayList">
     <void method="add">
      <string>https://marketplace.eclipse.org#1617241</string>
     </void>
    </object>
   </void>
   <void method="put">
    <string>org.jboss.tools.runtime.core.feature</string>
    <object class="java.util.ArrayList">
     <void method="add">
      <string>https://marketplace.eclipse.org#1617241</string>
     </void>
    </object>
   </void>
   <void method="put">
    <string>org.wso2.developerstudio.eclipse.esb.artifact.feature</string>
    <object class="java.util.ArrayList">
     <void method="add">
      <string>https://marketplace.eclipse.org#296419</string>
     </void>
    </object>
   </void>
   <void method="put">
    <string>org.jboss.tools.batch.feature</string>
    <object class="java.util.ArrayList">
     <void method="add">
      <string>https://marketplace.eclipse.org#1617241</string>
     </void>
    </object>
   </void>
   <void method="put">
    <string>org.eclipse.acute.feature</string>
    <object class="java.util.ArrayList">
     <void method="add">
      <string>https://marketplace.eclipse.org#3269902</string>
     </void>
    </object>
   </void>
   <void method="put">
    <string>org.eclipse.eclemma.feature</string>
    <object class="java.util.ArrayList">
     <void method="add">
      <string>https://marketplace.eclipse.org#2963451</string>
     </void>
    </object>
   </void>
   <void method="put">
    <string>org.apache.directory.studio.schemaeditor.feature</string>
    <object class="java.util.ArrayList">
     <void method="add">
      <string>https://marketplace.eclipse.org#319</string>
     </void>
    </object>
   </void>
   <void method="put">
    <string>org.hibernate.eclipse.feature</string>
    <object class="java.util.ArrayList">
     <void method="add">
      <string>https://marketplace.eclipse.org#1617241</string>
     </void>
    </object>
   </void>
   <void method="put">
    <string>org.eclipse.jst.server_adapters.feature</string>
    <object class="java.util.ArrayList">
     <void method="add">
      <string>https://marketplace.eclipse.org#2963451</string>
     </void>
    </object>
   </void>
   <void method="put">
    <string>com.jboss.devstudio.core.feature</string>
    <object class="java.util.ArrayList">
     <void method="add">
      <string>https://marketplace.eclipse.org#1616973</string>
     </void>
    </object>
   </void>
   <void method="put">
    <string>org.eclipse.viatra.integration.uml.feature.feature.group</string>
    <object class="java.util.ArrayList">
     <void method="add">
      <string>https://marketplace.eclipse.org#2292729</string>
     </void>
    </object>
   </void>
   <void method="put">
    <string>org.jboss.tools.forge.ext.feature</string>
    <object class="java.util.ArrayList">
     <void method="add">
      <string>https://marketplace.eclipse.org#1617241</string>
     </void>
    </object>
   </void>
   <void method="put">
    <string>com.equo.chromium.cef.feature.feature.group</string>
    <object class="java.util.ArrayList">
     <void method="add">
      <string>https://marketplace.eclipse.org#5642053</string>
     </void>
    </object>
   </void>
   <void method="put">
    <string>org.adichatz.feature</string>
    <object class="java.util.ArrayList">
     <void method="add">
      <string>https://marketplace.eclipse.org#941</string>
     </void>
    </object>
   </void>
   <void method="put">
    <string>org.eclipse.m2e.wtp.jaxrs.feature</string>
    <object class="java.util.ArrayList">
     <void method="add">
      <string>https://marketplace.eclipse.org#2963451</string>
     </void>
    </object>
   </void>
   <void method="put">
    <string>com.gwtplugins.eclipse.sdkbundle.gwt29.feature</string>
    <object class="java.util.ArrayList">
     <void method="add">
      <string>https://marketplace.eclipse.org#5579576</string>
     </void>
    </object>
   </void>
   <void method="put">
    <string>org.jboss.tools.community.central.feature</string>
    <object class="java.util.ArrayList">
     <void method="add">
      <string>https://marketplace.eclipse.org#1617241</string>
     </void>
    </object>
   </void>
   <void method="put">
    <string>org.eclipse.sirius.doc.feature</string>
    <object class="java.util.ArrayList">
     <void method="add">
      <string>https://marketplace.eclipse.org#1069</string>
     </void>
    </object>
   </void>
   <void method="put">
    <string>org.eclipse.sirius.specifier.ide.ui.acceleo</string>
    <object class="java.util.ArrayList">
     <void method="add">
      <string>https://marketplace.eclipse.org#1069</string>
     </void>
    </object>
   </void>
   <void method="put">
    <string>org.wso2.developerstudio.eclipse.capp.framework.feature</string>
    <object class="java.util.ArrayList">
     <void method="add">
      <string>https://marketplace.eclipse.org#296419</string>
     </void>
    </object>
   </void>
   <void method="put">
    <string>org.eclipse.jst.jsf.apache.trinidad.tagsupport.feature</string>
    <object class="java.util.ArrayList">
     <void method="add">
      <string>https://marketplace.eclipse.org#2963451</string>
     </void>
    </object>
   </void>
   <void method="put">
    <string>org.eclipse.sirius.runtime</string>
    <object class="java.util.ArrayList">
     <void method="add">
      <string>https://marketplace.eclipse.org#1069</string>
     </void>
    </object>
   </void>
   <void method="put">
    <string>org.eclipse.xtext.sdk</string>
    <object class="java.util.ArrayList">
     <void method="add">
      <string>https://marketplace.eclipse.org#1073</string>
     </void>
    </object>
   </void>
   <void method="put">
    <string>org.jboss.ide.eclipse.as.feature</string>
    <object class="java.util.ArrayList">
     <void method="add">
      <string>https://marketplace.eclipse.org#1617241</string>
     </void>
    </object>
   </void>
   <void method="put">
    <string>com.gwtplugins.eclipse.sdkbundle.gwt210.feature</string>
    <object class="java.util.ArrayList">
     <void method="add">
      <string>https://marketplace.eclipse.org#5579576</string>
     </void>
    </object>
   </void>
   <void method="put">
    <string>net.flexmojos.m2e.feature</string>
    <object class="java.util.ArrayList">
     <void method="add">
      <string>https://marketplace.eclipse.org#648556</string>
     </void>
    </object>
   </void>
   <void method="put">
    <string>org.jboss.tools.wtp.runtimes.tomcat.feature</string>
    <object class="java.util.ArrayList">
     <void method="add">
      <string>https://marketplace.eclipse.org#1617241</string>
     </void>
    </object>
   </void>
   <void method="put">
    <string>org.projectusus</string>
    <object class="java.util.ArrayList">
     <void method="add">
      <string>https://marketplace.eclipse.org#1089</string>
     </void>
    </object>
   </void>
   <void method="put">
    <string>org.eclipse.viatra.dse.feature.source.feature.group</string>
    <object class="java.util.ArrayList">
     <void method="add">
      <string>https://marketplace.eclipse.org#2292729</string>
     </void>
    </object>
   </void>
   <void method="put">
    <string>org.wso2.developerstudio.eclipse.carbonserver.42.feature</string>
    <object class="java.util.ArrayList">
     <void method="add">
      <string>https://marketplace.eclipse.org#296419</string>
     </void>
    </object>
   </void>
   <void method="put">
    <string>com.browserstack.eclipse.feature</string>
    <object class="java.util.ArrayList">
     <void method="add">
      <string>https://marketplace.eclipse.org#5599969</string>
     </void>
    </object>
   </void>
   <void method="put">
    <string>org.wso2.developerstudio.eclipse.gs.jaggery.feature</string>
    <object class="java.util.ArrayList">
     <void method="add">
      <string>https://marketplace.eclipse.org#296419</string>
     </void>
    </object>
   </void>
   <void method="put">
    <string>org.eclipse.tm.terminal.feature</string>
    <object class="java.util.ArrayList">
     <void method="add">
      <string>https://marketplace.eclipse.org#2963400</string>
     </void>
     <void method="add">
      <string>https://marketplace.eclipse.org#2963451</string>
     </void>
    </object>
   </void>
   <void method="put">
    <string>org.wso2.developerstudio.eclipse.carbonserver.30.feature</string>
    <object class="java.util.ArrayList">
     <void method="add">
      <string>https://marketplace.eclipse.org#296419</string>
     </void>
    </object>
   </void>
   <void method="put">
    <string>org.eclipse.sirius.runtime.ide.ui.acceleo</string>
    <object class="java.util.ArrayList">
     <void method="add">
      <string>https://marketplace.eclipse.org#1069</string>
     </void>
    </object>
   </void>
   <void method="put">
    <string>org.wso2.developerstudio.eclipse.appserver.feature</string>
    <object class="java.util.ArrayList">
     <void method="add">
      <string>https://marketplace.eclipse.org#296419</string>
     </void>
    </object>
   </void>
   <void method="put">
    <string>org.eclipse.wst.json_core.feature</string>
    <object class="java.util.ArrayList">
     <void method="add">
      <string>https://marketplace.eclipse.org#1617241</string>
     </void>
    </object>
   </void>
   <void method="put">
    <string>org.wso2.developerstudio.eclipse.usermgt.core.feature</string>
    <object class="java.util.ArrayList">
     <void method="add">
      <string>https://marketplace.eclipse.org#296419</string>
     </void>
    </object>
   </void>
   <void method="put">
    <string>org.moreunit.mock</string>
    <object class="java.util.ArrayList">
     <void method="add">
      <string>https://marketplace.eclipse.org#194</string>
     </void>
    </object>
   </void>
   <void method="put">
    <string>org.eclipse.embedcdt.templates.ad</string>
    <object class="java.util.ArrayList">
     <void method="add">
      <string>https://marketplace.eclipse.org#2593184</string>
     </void>
    </object>
   </void>
   <void method="put">
    <string>org.eclipse.wst.xml.xpath2.processor.feature</string>
    <object class="java.util.ArrayList">
     <void method="add">
      <string>https://marketplace.eclipse.org#2963451</string>
     </void>
    </object>
   </void>
   <void method="put">
    <string>org.eclipse.emf.ecoretools.sdk</string>
    <object class="java.util.ArrayList">
     <void method="add">
      <string>https://marketplace.eclipse.org#1069</string>
     </void>
    </object>
   </void>
   <void method="put">
    <string>org.nodeclipse.pluginslist.feature</string>
    <object class="java.util.ArrayList">
     <void method="add">
      <string>https://marketplace.eclipse.org#1451713</string>
     </void>
     <void method="add">
      <string>https://marketplace.eclipse.org#1512180</string>
     </void>
    </object>
   </void>
   <void method="put">
    <string>org.eclipse.emf.transaction.sdk</string>
    <object class="java.util.ArrayList">
     <void method="add">
      <string>https://marketplace.eclipse.org#1069</string>
     </void>
    </object>
   </void>
  </void>
  <void property="nodeKeyToIU">
   <void method="put">
    <string>https://marketplace.eclipse.org#5277018</string>
    <object class="java.util.ArrayList">
     <void method="add">
      <string>com.aspose.barcode.java.maven</string>
     </void>
    </object>
   </void>
   <void method="put">
    <string>https://marketplace.eclipse.org#807489</string>
    <object class="java.util.ArrayList">
     <void method="add">
      <string>org.jboss.tools.m2e.wro4j.feature</string>
     </void>
    </object>
   </void>
   <void method="put">
    <string>https://marketplace.eclipse.org#304652</string>
    <object class="java.util.ArrayList">
     <void method="add">
      <string>net.holmconsulting.ftp.server.feature</string>
     </void>
    </object>
   </void>
   <void method="put">
    <string>https://marketplace.eclipse.org#573</string>
    <object class="java.util.ArrayList">
     <void method="add">
      <string>org.eclipse.emf.cdo.sdk</string>
     </void>
     <void method="add">
      <string>org.eclipse.emf.cdo.lm</string>
     </void>
     <void method="add">
      <string>org.eclipse.net4j.sdk</string>
     </void>
    </object>
   </void>
   <void method="put">
    <string>https://marketplace.eclipse.org#2894763</string>
    <object class="java.util.ArrayList">
     <void method="add">
      <string>org.brainwy.liclipsetext.feature</string>
     </void>
    </object>
   </void>
   <void method="put">
    <string>https://marketplace.eclipse.org#5578890</string>
    <object class="java.util.ArrayList">
     <void method="add">
      <string>org.eclipse.wildwebdeveloper.feature</string>
     </void>
     <void method="add">
      <string>org.eclipse.wildwebdeveloper.embedder.node.feature</string>
     </void>
    </object>
   </void>
   <void method="put">
    <string>https://marketplace.eclipse.org#393519</string>
    <object class="java.util.ArrayList">
     <void method="add">
      <string>cn.ieclipse.adt.ext.feature</string>
     </void>
    </object>
   </void>
   <void method="put">
    <string>https://marketplace.eclipse.org#2799080</string>
    <object class="java.util.ArrayList">
     <void method="add">
      <string>org.eclipse.bpmn2.modeler</string>
     </void>
     <void method="add">
      <string>org.eclipse.bpmn2.modeler.runtime.jboss</string>
     </void>
     <void method="add">
      <string>org.eclipse.bpmn2.modeler.examples</string>
     </void>
    </object>
   </void>
   <void method="put">
    <string>https://marketplace.eclipse.org#1124</string>
    <object class="java.util.ArrayList">
     <void method="add">
      <string>org.infinitest.eclipse.feature</string>
     </void>
    </object>
   </void>
   <void method="put">
    <string>https://marketplace.eclipse.org#1166</string>
    <object class="java.util.ArrayList">
     <void method="add">
      <string>org.eclipse.wst.web_ui.feature.feature.group</string>
     </void>
    </object>
   </void>
   <void method="put">
    <string>https://marketplace.eclipse.org#1089</string>
    <object class="java.util.ArrayList">
     <void method="add">
      <string>org.projectusus</string>
     </void>
     <void method="add">
      <string>org.projectusus.autotestsuite</string>
     </void>
    </object>
   </void>
   <void method="put">
    <string>https://marketplace.eclipse.org#3348921</string>
    <object class="java.util.ArrayList">
     <void method="add">
      <string>com.wamas.ide.launching.feature</string>
     </void>
    </object>
   </void>
   <void method="put">
    <string>https://marketplace.eclipse.org#5277026</string>
    <object class="java.util.ArrayList">
     <void method="add">
      <string>com.aspose.tasks.java.maven</string>
     </void>
    </object>
   </void>
   <void method="put">
    <string>https://marketplace.eclipse.org#1286316</string>
    <object class="java.util.ArrayList">
     <void method="add">
      <string>org.jboss.tools.maven.profiles.feature</string>
     </void>
    </object>
   </void>
   <void method="put">
    <string>https://marketplace.eclipse.org#5277020</string>
    <object class="java.util.ArrayList">
     <void method="add">
      <string>com.aspose.email.java.maven</string>
     </void>
    </object>
   </void>
   <void method="put">
    <string>https://marketplace.eclipse.org#4014208</string>
    <object class="java.util.ArrayList">
     <void method="add">
      <string>fish.payara.eclipse.tools.server.feature</string>
     </void>
     <void method="add">
      <string>fish.payara.eclipse.tools.micro.feature</string>
     </void>
    </object>
   </void>
   <void method="put">
    <string>https://marketplace.eclipse.org#2394572</string>
    <object class="java.util.ArrayList">
     <void method="add">
      <string>org.eclipse.m2e.core.ui.phasesandgoals.feature</string>
     </void>
    </object>
   </void>
   <void method="put">
    <string>https://marketplace.eclipse.org#5223289</string>
    <object class="java.util.ArrayList">
     <void method="add">
      <string>de.jcup.hijson</string>
     </void>
    </object>
   </void>
   <void method="put">
    <string>https://marketplace.eclipse.org#5277009</string>
    <object class="java.util.ArrayList">
     <void method="add">
      <string>com.aspose.pdf.java.maven</string>
     </void>
    </object>
   </void>
   <void method="put">
    <string>https://marketplace.eclipse.org#296419</string>
    <object class="java.util.ArrayList">
     <void method="add">
      <string>org.wso2.developerstudio.eclipse.appfactory.feature</string>
     </void>
     <void method="add">
      <string>org.wso2.developerstudio.eclipse.appserver.artifact.feature</string>
     </void>
     <void method="add">
      <string>org.wso2.developerstudio.eclipse.appserver.feature</string>
     </void>
     <void method="add">
      <string>org.wso2.developerstudio.eclipse.artifact.library.feature</string>
     </void>
     <void method="add">
      <string>org.wso2.developerstudio.eclipse.bpel.feature</string>
     </void>
     <void method="add">
      <string>org.wso2.developerstudio.eclipse.bpel.artifact.feature</string>
     </void>
     <void method="add">
      <string>org.wso2.developerstudio.eclipse.brs.artifact.feature</string>
     </void>
     <void method="add">
      <string>org.wso2.developerstudio.eclipse.capp.framework.feature</string>
     </void>
     <void method="add">
      <string>org.wso2.developerstudio.eclipse.carbon.uibundle.artifact.feature</string>
     </void>
     <void method="add">
      <string>org.wso2.developerstudio.eclipse.carbonserver.30.feature</string>
     </void>
     <void method="add">
      <string>org.wso2.developerstudio.eclipse.carbonserver.31.feature</string>
     </void>
     <void method="add">
      <string>org.wso2.developerstudio.eclipse.carbonserver.32.feature</string>
     </void>
     <void method="add">
      <string>org.wso2.developerstudio.eclipse.carbonserver.40.feature</string>
     </void>
     <void method="add">
      <string>org.wso2.developerstudio.eclipse.carbonserver.42.feature</string>
     </void>
     <void method="add">
      <string>org.wso2.developerstudio.eclipse.carbonserver.44.feature</string>
     </void>
     <void method="add">
      <string>org.wso2.developerstudio.eclipse.carbonserver.remote.feature</string>
     </void>
     <void method="add">
      <string>org.wso2.developerstudio.eclipse.distribution.project.feature</string>
     </void>
     <void method="add">
      <string>org.wso2.developerstudio.eclipse.ds.artifact.feature</string>
     </void>
     <void method="add">
      <string>org.wso2.developerstudio.eclipse.ds.feature</string>
     </void>
     <void method="add">
      <string>org.wso2.developerstudio.eclipse.esb.artifact.feature</string>
     </void>
     <void method="add">
      <string>org.wso2.developerstudio.eclipse.esb.graphical.editor.feature</string>
     </void>
     <void method="add">
      <string>org.wso2.developerstudio.eclipse.framework.core.feature</string>
     </void>
     <void method="add">
      <string>org.wso2.developerstudio.eclipse.framework.samples.feature</string>
     </void>
     <void method="add">
      <string>org.wso2.developerstudio.eclipse.gadget.artifact.feature</string>
     </void>
     <void method="add">
      <string>org.wso2.developerstudio.eclipse.gs.jaggery.feature</string>
     </void>
     <void method="add">
      <string>org.wso2.developerstudio.eclipse.jaggery.artifact.feature</string>
     </void>
     <void method="add">
      <string>org.wso2.developerstudio.eclipse.security.artifact.feature</string>
     </void>
     <void method="add">
      <string>org.wso2.developerstudio.eclipse.registry.artifact.feature</string>
     </void>
     <void method="add">
      <string>org.wso2.developerstudio.eclipse.registry.connector.feature</string>
     </void>
     <void method="add">
      <string>org.wso2.developerstudio.eclipse.registry.feature</string>
     </void>
     <void method="add">
      <string>org.wso2.developerstudio.eclipse.server.framework.feature</string>
     </void>
     <void method="add">
      <string>org.wso2.developerstudio.eclipse.usermgt.core.feature</string>
     </void>
     <void method="add">
      <string>org.jboss.tools.smooks.feature</string>
     </void>
     <void method="add">
      <string>org.smooks.edi.editor-feature</string>
     </void>
     <void method="add">
      <string>org.wso2.soapui.feature</string>
     </void>
     <void method="add">
      <string>org.wso2.tcpmon.feature</string>
     </void>
     <void method="add">
      <string>org.wso2.developerstudio.eclipse.analytics.artifact.feature</string>
     </void>
     <void method="add">
      <string>org.wso2.developerstudio.eclipse.apim.feature</string>
     </void>
    </object>
   </void>
   <void method="put">
    <string>https://marketplace.eclipse.org#5277005</string>
    <object class="java.util.ArrayList">
     <void method="add">
      <string>com.aspose.cells.java.maven</string>
     </void>
    </object>
   </void>
   <void method="put">
    <string>https://marketplace.eclipse.org#1549</string>
    <object class="java.util.ArrayList">
     <void method="add">
      <string>org.testng.eclipse</string>
     </void>
     <void method="add">
      <string>org.testng.eclipse.maven.feature</string>
     </void>
    </object>
   </void>
   <void method="put">
    <string>https://marketplace.eclipse.org#4101183</string>
    <object class="java.util.ArrayList">
     <void method="add">
      <string>de.jcup.yamleditor</string>
     </void>
    </object>
   </void>
   <void method="put">
    <string>https://marketplace.eclipse.org#1451713</string>
    <object class="java.util.ArrayList">
     <void method="add">
      <string>org.nodeclipse.pluginslist.feature</string>
     </void>
     <void method="add">
      <string>org.nodeclipse.enide.maven.feature</string>
     </void>
     <void method="add">
      <string>de.bastiankrol.startexplorer.feature</string>
     </void>
     <void method="add">
      <string>pm.eclipse.editbox.feature</string>
     </void>
    </object>
   </void>
   <void method="put">
    <string>https://marketplace.eclipse.org#319</string>
    <object class="java.util.ArrayList">
     <void method="add">
      <string>org.apache.directory.studio.ldapbrowser.feature</string>
     </void>
     <void method="add">
      <string>org.apache.directory.studio.ldifeditor.feature</string>
     </void>
     <void method="add">
      <string>org.apache.directory.studio.schemaeditor.feature</string>
     </void>
     <void method="add">
      <string>org.apache.directory.studio.apacheds.feature</string>
     </void>
    </object>
   </void>
   <void method="put">
    <string>https://marketplace.eclipse.org#5507008</string>
    <object class="java.util.ArrayList">
     <void method="add">
      <string>com.devepos.adt.codesearch</string>
     </void>
    </object>
   </void>
   <void method="put">
    <string>https://marketplace.eclipse.org#1616973</string>
    <object class="java.util.ArrayList">
     <void method="add">
      <string>com.jboss.devstudio.core.feature</string>
     </void>
     <void method="add">
      <string>com.jboss.devstudio.fuse.feature</string>
     </void>
    </object>
   </void>
   <void method="put">
    <string>https://marketplace.eclipse.org#84997</string>
    <object class="java.util.ArrayList">
     <void method="add">
      <string>org.freejava.javasourceattacher.feature</string>
     </void>
    </object>
   </void>
   <void method="put">
    <string>https://marketplace.eclipse.org#1073</string>
    <object class="java.util.ArrayList">
     <void method="add">
      <string>org.eclipse.xtext.sdk</string>
     </void>
    </object>
   </void>
   <void method="put">
    <string>https://marketplace.eclipse.org#194</string>
    <object class="java.util.ArrayList">
     <void method="add">
      <string>org.moreunit</string>
     </void>
     <void method="add">
      <string>org.moreunit.mock</string>
     </void>
     <void method="add">
      <string>org.moreunit.light</string>
     </void>
    </object>
   </void>
   <void method="put">
    <string>https://marketplace.eclipse.org#648556</string>
    <object class="java.util.ArrayList">
     <void method="add">
      <string>net.flexmojos.m2e.feature</string>
     </void>
    </object>
   </void>
   <void method="put">
    <string>https://marketplace.eclipse.org#5599969</string>
    <object class="java.util.ArrayList">
     <void method="add">
      <string>com.browserstack.eclipse.feature</string>
     </void>
    </object>
   </void>
   <void method="put">
    <string>https://marketplace.eclipse.org#279</string>
    <object class="java.util.ArrayList">
     <void method="add">
      <string>org.eclipse.objectteams.otdt.feature.group</string>
     </void>
     <void method="add">
      <string>org.eclipse.objectteams.otequinox.feature.group</string>
     </void>
    </object>
   </void>
   <void method="put">
    <string>https://marketplace.eclipse.org#677</string>
    <object class="java.util.ArrayList">
     <void method="add">
      <string>org.eclipse.swtbot</string>
     </void>
     <void method="add">
      <string>org.eclipse.swtbot.eclipse</string>
     </void>
     <void method="add">
      <string>org.eclipse.swtbot.eclipse.gef</string>
     </void>
     <void method="add">
      <string>org.eclipse.swtbot.ide</string>
     </void>
    </object>
   </void>
   <void method="put">
    <string>https://marketplace.eclipse.org#169937</string>
    <object class="java.util.ArrayList">
     <void method="add">
      <string>org.eclipse.etrice.feature</string>
     </void>
     <void method="add">
      <string>org.eclipse.etrice.cdt_integration.feature</string>
     </void>
    </object>
   </void>
   <void method="put">
    <string>https://marketplace.eclipse.org#2963400</string>
    <object class="java.util.ArrayList">
     <void method="add">
      <string>org.eclipse.wst.web_ui.feature</string>
     </void>
     <void method="add">
      <string>org.eclipse.wst.web_js_support.feature</string>
     </void>
     <void method="add">
      <string>org.eclipse.wst.xml_ui.feature</string>
     </void>
     <void method="add">
      <string>org.eclipse.wst.xsl.feature</string>
     </void>
     <void method="add">
      <string>org.eclipse.tips.feature</string>
     </void>
     <void method="add">
      <string>org.eclipse.egit</string>
     </void>
     <void method="add">
      <string>org.eclipse.egit.gitflow.feature</string>
     </void>
     <void method="add">
      <string>org.eclipse.tm.terminal.feature</string>
     </void>
     <void method="add">
      <string>org.eclipse.wildwebdeveloper.feature</string>
     </void>
     <void method="add">
      <string>org.eclipse.wildwebdeveloper.embedder.node.feature</string>
     </void>
     <void method="add">
      <string>org.eclipse.wst.server_ui.feature</string>
     </void>
     <void method="add">
      <string>org.eclipse.wst.server_adapters.feature</string>
     </void>
     <void method="add">
      <string>org.eclipse.wst.json_ui.feature</string>
     </void>
    </object>
   </void>
   <void method="put">
    <string>https://marketplace.eclipse.org#3269902</string>
    <object class="java.util.ArrayList">
     <void method="add">
      <string>org.eclipse.acute.feature</string>
     </void>
    </object>
   </void>
   <void method="put">
    <string>https://marketplace.eclipse.org#1069</string>
    <object class="java.util.ArrayList">
     <void method="add">
      <string>fr.obeo.dsl.designer.ce.feature</string>
     </void>
     <void method="add">
      <string>org.eclipse.emf.compare.ide.ui</string>
     </void>
     <void method="add">
      <string>org.eclipse.emf.ecoretools.sdk</string>
     </void>
     <void method="add">
      <string>org.eclipse.emf.transaction.sdk</string>
     </void>
     <void method="add">
      <string>org.eclipse.emf.validation.sdk</string>
     </void>
     <void method="add">
      <string>org.eclipse.gmf.runtime.sdk</string>
     </void>
     <void method="add">
      <string>org.eclipse.sirius.doc.feature</string>
     </void>
     <void method="add">
      <string>org.eclipse.sirius.runtime</string>
     </void>
     <void method="add">
      <string>org.eclipse.sirius.runtime.acceleo</string>
     </void>
     <void method="add">
      <string>org.eclipse.sirius.runtime.ide.eef</string>
     </void>
     <void method="add">
      <string>org.eclipse.sirius.runtime.ide.ui</string>
     </void>
     <void method="add">
      <string>org.eclipse.sirius.runtime.ide.ui.acceleo</string>
     </void>
     <void method="add">
      <string>org.eclipse.sirius.samples</string>
     </void>
     <void method="add">
      <string>org.eclipse.sirius.specifier.ide.ui</string>
     </void>
     <void method="add">
      <string>org.eclipse.sirius.specifier.ide.ui.acceleo</string>
     </void>
    </object>
   </void>
   <void method="put">
    <string>https://marketplace.eclipse.org#945</string>
    <object class="java.util.ArrayList">
     <void method="add">
      <string>org.antlr.v4</string>
     </void>
     <void method="add">
      <string>jsonedit-feature</string>
     </void>
    </object>
   </void>
   <void method="put">
    <string>https://marketplace.eclipse.org#1220</string>
    <object class="java.util.ArrayList">
     <void method="add">
      <string>bndtools.main.feature</string>
     </void>
     <void method="add">
      <string>bndtools.m2e.feature</string>
     </void>
     <void method="add">
      <string>bndtools.pde.feature</string>
     </void>
    </object>
   </void>
   <void method="put">
    <string>https://marketplace.eclipse.org#1789419</string>
    <object class="java.util.ArrayList">
     <void method="add">
      <string>org.eclipse.m2e.wtp.feature</string>
     </void>
    </object>
   </void>
   <void method="put">
    <string>https://marketplace.eclipse.org#3103502</string>
    <object class="java.util.ArrayList">
     <void method="add">
      <string>com.eco.bio7.image.feature</string>
     </void>
     <void method="add">
      <string>com.eco.bio7.ijmacroedit.feature</string>
     </void>
     <void method="add">
      <string>com.eco.bio7.jfxswt.feature</string>
     </void>
    </object>
   </void>
   <void method="put">
    <string>https://marketplace.eclipse.org#2292729</string>
    <object class="java.util.ArrayList">
     <void method="add">
      <string>org.eclipse.viatra.query.sdk.feature.source.feature.group</string>
     </void>
     <void method="add">
      <string>org.eclipse.viatra.dse.feature.source.feature.group</string>
     </void>
     <void method="add">
      <string>org.eclipse.viatra.query.sdk.extensions.feature</string>
     </void>
     <void method="add">
      <string>org.eclipse.viatra.integration.uml.feature.feature.group</string>
     </void>
    </object>
   </void>
   <void method="put">
    <string>https://marketplace.eclipse.org#2963451</string>
    <object class="java.util.ArrayList">
     <void method="add">
      <string>org.eclipse.buildship</string>
     </void>
     <void method="add">
      <string>org.eclipse.eclemma.feature</string>
     </void>
     <void method="add">
      <string>org.eclipse.egit</string>
     </void>
     <void method="add">
      <string>org.eclipse.egit.gitflow.feature</string>
     </void>
     <void method="add">
      <string>org.eclipse.jpt.common.eclipselink.feature</string>
     </void>
     <void method="add">
      <string>org.eclipse.jpt.common.feature</string>
     </void>
     <void method="add">
      <string>org.eclipse.jpt.jaxb.eclipselink.feature</string>
     </void>
     <void method="add">
      <string>org.eclipse.jpt.jaxb.feature</string>
     </void>
     <void method="add">
      <string>org.eclipse.jpt.jpa.eclipselink.feature</string>
     </void>
     <void method="add">
      <string>org.eclipse.jsf.feature</string>
     </void>
     <void method="add">
      <string>org.eclipse.jst.jsf.apache.trinidad.tagsupport.feature</string>
     </void>
     <void method="add">
      <string>org.eclipse.jst.enterprise_ui.feature</string>
     </void>
     <void method="add">
      <string>org.eclipse.jst.server_adapters.ext.feature</string>
     </void>
     <void method="add">
      <string>org.eclipse.jst.server_adapters.feature</string>
     </void>
     <void method="add">
      <string>org.eclipse.jst.server_ui.feature</string>
     </void>
     <void method="add">
      <string>org.eclipse.jst.web_js_support.feature</string>
     </void>
     <void method="add">
      <string>org.eclipse.jst.web_ui.feature</string>
     </void>
     <void method="add">
      <string>org.eclipse.jst.ws.axis2tools.feature</string>
     </void>
     <void method="add">
      <string>org.eclipse.jst.ws.cxf.feature</string>
     </void>
     <void method="add">
      <string>org.eclipse.jst.ws.jaxws.dom.feature</string>
     </void>
     <void method="add">
      <string>org.eclipse.jst.ws.jaxws.feature</string>
     </void>
     <void method="add">
      <string>org.eclipse.linuxtools.docker.feature</string>
     </void>
     <void method="add">
      <string>org.eclipse.m2e.lemminx.feature</string>
     </void>
     <void method="add">
      <string>org.eclipse.m2e.logback.feature</string>
     </void>
     <void method="add">
      <string>org.eclipse.m2e.wtp.feature</string>
     </void>
     <void method="add">
      <string>org.eclipse.m2e.wtp.jaxrs.feature</string>
     </void>
     <void method="add">
      <string>org.eclipse.m2e.wtp.jpa.feature</string>
     </void>
     <void method="add">
      <string>org.eclipse.m2e.wtp.jsf.feature</string>
     </void>
     <void method="add">
      <string>org.eclipse.mylyn.wikitext.editors_feature</string>
     </void>
     <void method="add">
      <string>org.eclipse.tips.feature</string>
     </void>
     <void method="add">
      <string>org.eclipse.tm.terminal.feature</string>
     </void>
     <void method="add">
      <string>org.eclipse.wildwebdeveloper.feature</string>
     </void>
     <void method="add">
      <string>org.eclipse.wildwebdeveloper.embedder.node.feature</string>
     </void>
     <void method="add">
      <string>org.eclipse.wst.json_ui.feature</string>
     </void>
     <void method="add">
      <string>org.eclipse.wst.server_adapters.feature</string>
     </void>
     <void method="add">
      <string>org.eclipse.wst.server_ui.feature</string>
     </void>
     <void method="add">
      <string>org.eclipse.wst.web_js_support.feature</string>
     </void>
     <void method="add">
      <string>org.eclipse.wst.web_ui.feature</string>
     </void>
     <void method="add">
      <string>org.eclipse.wst.xml.xpath2.processor.feature</string>
     </void>
     <void method="add">
      <string>org.eclipse.wst.xml_ui.feature</string>
     </void>
     <void method="add">
      <string>org.eclipse.wst.xsl.feature</string>
     </void>
    </object>
   </void>
   <void method="put">
    <string>https://marketplace.eclipse.org#5305264</string>
    <object class="java.util.ArrayList">
     <void method="add">
      <string>ContextQuickie2</string>
     </void>
    </object>
   </void>
   <void method="put">
    <string>https://marketplace.eclipse.org#3503691</string>
    <object class="java.util.ArrayList">
     <void method="add">
      <string>eu.jsparrow.202106.feature</string>
     </void>
    </object>
   </void>
   <void method="put">
    <string>https://marketplace.eclipse.org#1617241</string>
    <object class="java.util.ArrayList">
     <void method="add">
      <string>org.jboss.tools.usage.feature</string>
     </void>
     <void method="add">
      <string>org.eclipse.buildship</string>
     </void>
     <void method="add">
      <string>org.eclipse.linuxtools.docker.feature</string>
     </void>
     <void method="add">
      <string>org.eclipse.wildwebdeveloper.feature</string>
     </void>
     <void method="add">
      <string>org.eclipse.wst.jsdt.chromium.debug.feature</string>
     </void>
     <void method="add">
      <string>org.eclipse.wst.jsdt.feature</string>
     </void>
     <void method="add">
      <string>org.eclipse.wst.json_core.feature</string>
     </void>
     <void method="add">
      <string>org.eclipse.wst.json_ui.feature</string>
     </void>
     <void method="add">
      <string>org.fusesource.ide.camel.editor.feature</string>
     </void>
     <void method="add">
      <string>org.fusesource.ide.core.feature</string>
     </void>
     <void method="add">
      <string>org.fusesource.ide.jmx.feature</string>
     </void>
     <void method="add">
      <string>org.fusesource.ide.server.extensions.feature</string>
     </void>
     <void method="add">
      <string>org.fusesource.ide.syndesis.extension.feature</string>
     </void>
     <void method="add">
      <string>org.hibernate.eclipse.feature</string>
     </void>
     <void method="add">
      <string>org.jboss.ide.eclipse.archives.feature</string>
     </void>
     <void method="add">
      <string>org.jboss.ide.eclipse.as.feature</string>
     </void>
     <void method="add">
      <string>org.jboss.tools.batch.feature</string>
     </void>
     <void method="add">
      <string>org.jboss.tools.cdi.deltaspike.feature</string>
     </void>
     <void method="add">
      <string>org.jboss.tools.cdi.feature</string>
     </void>
     <void method="add">
      <string>org.jboss.tools.cdi.microprofile.feature</string>
     </void>
     <void method="add">
      <string>org.jboss.tools.common.jdt.feature</string>
     </void>
     <void method="add">
      <string>org.jboss.tools.common.launcher.feature</string>
     </void>
     <void method="add">
      <string>org.jboss.tools.community.central.feature</string>
     </void>
     <void method="add">
      <string>org.jboss.tools.community.project.examples.feature</string>
     </void>
     <void method="add">
      <string>org.jboss.tools.forge.ext.feature</string>
     </void>
     <void method="add">
      <string>org.jboss.tools.forge.feature</string>
     </void>
     <void method="add">
      <string>org.jboss.tools.forge.m2e.feature</string>
     </void>
     <void method="add">
      <string>org.jboss.tools.foundation.feature</string>
     </void>
     <void method="add">
      <string>org.jboss.tools.foundation.security.linux.feature</string>
     </void>
     <void method="add">
      <string>org.jboss.tools.fuse.transformation.feature</string>
     </void>
     <void method="add">
      <string>org.jboss.tools.jmx.feature</string>
     </void>
     <void method="add">
      <string>org.jboss.tools.jsf.feature</string>
     </void>
     <void method="add">
      <string>org.jboss.tools.jst.angularjs.feature</string>
     </void>
     <void method="add">
      <string>org.jboss.tools.jst.feature</string>
     </void>
     <void method="add">
      <string>org.jboss.tools.jst.jsdt.feature</string>
     </void>
     <void method="add">
      <string>org.jboss.tools.maven.cdi.feature</string>
     </void>
     <void method="add">
      <string>org.jboss.tools.maven.feature</string>
     </void>
     <void method="add">
      <string>org.jboss.tools.maven.hibernate.feature</string>
     </void>
     <void method="add">
      <string>org.jboss.tools.maven.jbosspackaging.feature</string>
     </void>
     <void method="add">
      <string>org.jboss.tools.maven.jdt.feature</string>
     </void>
     <void method="add">
      <string>org.jboss.tools.maven.project.examples.feature</string>
     </void>
     <void method="add">
      <string>org.jboss.tools.maven.sourcelookup.feature</string>
     </void>
     <void method="add">
      <string>org.jboss.tools.maven.springboot.feature</string>
     </void>
     <void method="add">
      <string>org.jboss.tools.openshift.cdk.feature</string>
     </void>
     <void method="add">
      <string>org.jboss.tools.openshift.egit.integration.feature</string>
     </void>
     <void method="add">
      <string>org.jboss.tools.openshift.js.feature</string>
     </void>
     <void method="add">
      <string>org.jboss.tools.openshift.feature</string>
     </void>
     <void method="add">
      <string>org.jboss.tools.project.examples.feature</string>
     </void>
     <void method="add">
      <string>org.jboss.tools.quarkus.feature</string>
     </void>
     <void method="add">
      <string>org.jboss.tools.richfaces.feature</string>
     </void>
     <void method="add">
      <string>org.jboss.tools.runtime.core.feature</string>
     </void>
     <void method="add">
      <string>org.jboss.tools.stacks.core.feature</string>
     </void>
     <void method="add">
      <string>org.jboss.tools.vpe.feature</string>
     </void>
     <void method="add">
      <string>org.jboss.tools.websockets.feature</string>
     </void>
     <void method="add">
      <string>org.jboss.tools.ws.jaxrs.feature</string>
     </void>
     <void method="add">
      <string>org.jboss.tools.ws.jaxws.feature</string>
     </void>
     <void method="add">
      <string>org.jboss.tools.wtp.runtimes.tomcat.feature</string>
     </void>
    </object>
   </void>
   <void method="put">
    <string>https://marketplace.eclipse.org#941</string>
    <object class="java.util.ArrayList">
     <void method="add">
      <string>org.adichatz.feature</string>
     </void>
    </object>
   </void>
   <void method="put">
    <string>https://marketplace.eclipse.org#5321178</string>
    <object class="java.util.ArrayList">
     <void method="add">
      <string>org.eclipse.m2e.feature</string>
     </void>
     <void method="add">
      <string> org.eclipse.m2e.pde.feature</string>
     </void>
    </object>
   </void>
   <void method="put">
    <string>https://marketplace.eclipse.org#2593184</string>
    <object class="java.util.ArrayList">
     <void method="add">
      <string>org.eclipse.embedcdt.managedbuild.cross.arm</string>
     </void>
     <void method="add">
      <string>org.eclipse.embedcdt.managedbuild.cross.riscv</string>
     </void>
     <void method="add">
      <string>org.eclipse.embedcdt.codered</string>
     </void>
     <void method="add">
      <string>org.eclipse.embedcdt.debug.gdbjtag.jlink</string>
     </void>
     <void method="add">
      <string>org.eclipse.embedcdt.debug.gdbjtag.openocd</string>
     </void>
     <void method="add">
      <string>org.eclipse.embedcdt.debug.gdbjtag.pyocd</string>
     </void>
     <void method="add">
      <string>org.eclipse.embedcdt.debug.gdbjtag.qemu</string>
     </void>
     <void method="add">
      <string>org.eclipse.embedcdt.templates.stm</string>
     </void>
     <void method="add">
      <string>org.eclipse.embedcdt.templates.sifive</string>
     </void>
     <void method="add">
      <string>org.eclipse.embedcdt.templates.ad</string>
     </void>
     <void method="add">
      <string>org.eclipse.embedcdt.packs</string>
     </void>
     <void method="add">
      <string>org.eclipse.embedcdt.templates.cortexm</string>
     </void>
     <void method="add">
      <string>org.eclipse.embedcdt.templates.xpack</string>
     </void>
    </object>
   </void>
   <void method="put">
    <string>https://marketplace.eclipse.org#1512180</string>
    <object class="java.util.ArrayList">
     <void method="add">
      <string>org.nodeclipse.pluginslist.feature</string>
     </void>
     <void method="add">
      <string>org.nodeclipse.enide.gradle.feature</string>
     </void>
     <void method="add">
      <string>org.nodeclipse.enide.editors.gradle.feature</string>
     </void>
     <void method="add">
      <string>de.bastiankrol.startexplorer.feature</string>
     </void>
     <void method="add">
      <string>pm.eclipse.editbox.feature</string>
     </void>
    </object>
   </void>
   <void method="put">
    <string>https://marketplace.eclipse.org#4002</string>
    <object class="java.util.ArrayList">
     <void method="add">
      <string>org.eclipse.net4j.sdk</string>
     </void>
    </object>
   </void>
   <void method="put">
    <string>https://marketplace.eclipse.org#5642053</string>
    <object class="java.util.ArrayList">
     <void method="add">
      <string>com.equo.chromium.cef.feature.feature.group</string>
     </void>
     <void method="add">
      <string>com.equo.chromium.feature.feature.group</string>
     </void>
     <void method="add">
      <string>com.equo.chromium.eclipse.feature.feature.group</string>
     </void>
    </object>
   </void>
   <void method="put">
    <string>https://marketplace.eclipse.org#5277033</string>
    <object class="java.util.ArrayList">
     <void method="add">
      <string>com.aspose.slides.java.maven</string>
     </void>
    </object>
   </void>
   <void method="put">
    <string>https://marketplace.eclipse.org#5579576</string>
    <object class="java.util.ArrayList">
     <void method="add">
      <string>com.github.sdbg.feature</string>
     </void>
     <void method="add">
      <string>com.gwtplugins.eclipse.sdkbundle.gwt27.feature</string>
     </void>
     <void method="add">
      <string>com.gwtplugins.eclipse.sdkbundle.gwt28.feature</string>
     </void>
     <void method="add">
      <string>com.gwtplugins.eclipse.sdkbundle.gwt29.feature</string>
     </void>
     <void method="add">
      <string>com.gwtplugins.eclipse.sdkbundle.gwt210.feature</string>
     </void>
     <void method="add">
      <string>com.gwtplugins.eclipse.suite.v3.feature</string>
     </void>
    </object>
   </void>
  </void>
 </object>
</java>
